{
  "method": "textDocument/rename",
  "result": {
    "changes": {
      "<PLACEHOLDER_PROJECT_URL>/__fixtures__/locals.js": [
        {
          "range": {
            "start": {
              "line": 14,
              "character": 4
            },
            "end": {
              "line": 14,
              "character": 12
            }
          },
          "newText": "{x: NEW_NAME, y}"
        },
        {
          "range": {
            "start": {
              "line": 15,
              "character": 25
            },
            "end": {
              "line": 15,
              "character": 26
            }
          },
          "newText": "x: NEW_NAME"
        },
        {
          "range": {
            "start": {
              "line": 18,
              "character": 7
            },
            "end": {
              "line": 18,
              "character": 8
            }
          },
          "newText": "NEW_NAME"
        }
      ]
    }
  }
}
